py_scibec_openapi_client/__init__.py
py_scibec_openapi_client/api_client.py
py_scibec_openapi_client/api_response.py
py_scibec_openapi_client/configuration.py
py_scibec_openapi_client/exceptions.py
py_scibec_openapi_client/py.typed
py_scibec_openapi_client/rest.py
py_scibec_openapi_client/api/__init__.py
py_scibec_openapi_client/api/access_account_controller_api.py
py_scibec_openapi_client/api/access_config_controller_api.py
py_scibec_openapi_client/api/beamline_controller_api.py
py_scibec_openapi_client/api/dataset_controller_api.py
py_scibec_openapi_client/api/device_controller_api.py
py_scibec_openapi_client/api/experiment_account_controller_api.py
py_scibec_openapi_client/api/experiment_controller_api.py
py_scibec_openapi_client/api/functional_account_controller_api.py
py_scibec_openapi_client/api/nx_entity_controller_api.py
py_scibec_openapi_client/api/oidc_controller_api.py
py_scibec_openapi_client/api/scan_controller_api.py
py_scibec_openapi_client/api/scan_data_controller_api.py
py_scibec_openapi_client/api/session_controller_api.py
py_scibec_openapi_client/api/user_controller_api.py
py_scibec_openapi_client/models/__init__.py
py_scibec_openapi_client/models/access_account.py
py_scibec_openapi_client/models/access_account_fields.py
py_scibec_openapi_client/models/access_account_fields_one_of.py
py_scibec_openapi_client/models/access_account_filter.py
py_scibec_openapi_client/models/access_account_filter1.py
py_scibec_openapi_client/models/access_account_filter_order.py
py_scibec_openapi_client/models/access_account_partial.py
py_scibec_openapi_client/models/access_account_with_relations.py
py_scibec_openapi_client/models/access_config.py
py_scibec_openapi_client/models/access_config_fields.py
py_scibec_openapi_client/models/access_config_fields_one_of.py
py_scibec_openapi_client/models/access_config_filter.py
py_scibec_openapi_client/models/access_config_filter1.py
py_scibec_openapi_client/models/access_config_include_filter_inner.py
py_scibec_openapi_client-1.15.0.dist-info/METADATA
py_scibec_openapi_client-1.15.0.dist-info/WHEEL
py_scibec_openapi_client-1.15.0.dist-info/top_level.txt
py_scibec_openapi_client-1.15.0.dist-info/RECORD
