Metadata-Version: 2.1
Name: py-scibec-openapi-client
Version: 1.15.0
Summary: scibec
Home-page: 
Author: Klaus Wakonig
Author-email: klaus.wakonig@psi.ch
Keywords: OpenAPI,OpenAPI-Generator,scibec
Requires-Dist: urllib3<2.1.0,>=1.25.3
Requires-Dist: python-dateutil
Requires-Dist: pydantic>=2
Requires-Dist: typing-extensions>=4.7.1
